setup.py
RBACBWC.egg-info/PKG-INFO
RBACBWC.egg-info/SOURCES.txt
RBACBWC.egg-info/dependency_links.txt
RBACBWC.egg-info/not-zip-safe
RBACBWC.egg-info/requires.txt
RBACBWC.egg-info/top_level.txt
rbacbwc/__init__.py
rbacbwc/lib/__init__.py
rbacbwc/lib/queries.py
rbacbwc_ta/__init__.py
rbacbwc_ta/application.py
rbacbwc_ta/config/__init__.py
rbacbwc_ta/config/settings.py
rbacbwc_ta/model/__init__.py
rbacbwc_ta/model/entities.py
rbacbwc_ta/model/schema.py
rbacbwc_ta/tests/__init__.py
rbacbwc_ta/tests/helpers.py
rbacbwc_ta/tests/test_applications.py
rbacbwc_ta/tests/test_bundles.py
rbacbwc_ta/tests/test_groups.py
rbacbwc_ta/tests/test_permissions.py
rbacbwc_ta/tests/test_prefix.py
rbacbwc_ta/tests/test_users.py