Metadata-Version: 1.0
Name: RBACBWC
Version: 0.1.0
Summary: A BlazeWeb component implimenting role based access control with SQLAlchemy
Home-page: https://bitbucket.org/rsyring/rbacbwc/
Author: Randy Syring
Author-email: rsyring@gmail.com
License: BSD
Platform: UNKNOWN
Classifier: Development Status :: 3 - Alpha
Classifier: Intended Audience :: Developers
Classifier: License :: OSI Approved :: BSD License
